ibasis/__init__.py
ibasis/fio.py
ibasis/iaffine.py
ibasis/ibasic.py
ibasis/icolor.py
ibasis/idraw.py
ibasis/idtbs.py
ibasis/ifile.py
ibasis/iformat.py
ibasis/iimg.py
ibasis/ilmdb.py
ibasis/ilog.py
ibasis/imath.py
ibasis/imetric.py
ibasis/imgalg.py
ibasis/imultiproc.py
ibasis/inusc.py
ibasis/iopen3d.py
ibasis/ipath.py
ibasis/ipcd.py
ibasis/iplt.py
ibasis/ipoint.py
ibasis/iprofile.py
ibasis/iserialization.py
ibasis/ishell.py
ibasis/itimeutils.py
ibasis/itorch.py
ibasis-0.0.5.dist-info/LICENSE
ibasis-0.0.5.dist-info/METADATA
ibasis-0.0.5.dist-info/WHEEL
ibasis-0.0.5.dist-info/top_level.txt
ibasis-0.0.5.dist-info/RECORD
